ckanext/__init__.py
ckanext/unfold/__init__.py
ckanext/unfold/config.py
ckanext/unfold/config_declaration.yaml
ckanext/unfold/exception.py
ckanext/unfold/plugin.py
ckanext/unfold/types.py
ckanext/unfold/utils.py
ckanext/unfold/adapters/_7z.py
ckanext/unfold/adapters/__init__.py
ckanext/unfold/adapters/ar.py
ckanext/unfold/adapters/base.py
ckanext/unfold/adapters/rar.py
ckanext/unfold/adapters/rpm.py
ckanext/unfold/adapters/tar.py
ckanext/unfold/adapters/zip.py
ckanext/unfold/assets/webassets.yml
ckanext/unfold/assets/css/unfold.css
ckanext/unfold/assets/js/unfold-init-jstree.js
ckanext/unfold/assets/vendor/jstree.min.css
ckanext/unfold/assets/vendor/jstree.min.js
ckanext/unfold/logic/action.py
ckanext/unfold/logic/schema.py
ckanext/unfold/logic/validators.py
ckanext/unfold/templates/unfold_form.html
ckanext/unfold/templates/unfold_preview.html
ckanext/unfold/tests/__init__.py
ckanext/unfold/tests/test_unfold.py
ckanext_unfold-2.1.6.dist-info/licenses/LICENSE
ckanext_unfold-2.1.6.dist-info/METADATA
ckanext_unfold-2.1.6.dist-info/WHEEL
ckanext_unfold-2.1.6.dist-info/entry_points.txt
ckanext_unfold-2.1.6.dist-info/top_level.txt
ckanext_unfold-2.1.6.dist-info/RECORD
