Metadata-Version: 2.4
Name: ckanext-unfold
Version: 2.1.6
Summary: Provides previews for multiple archive formats
Author-email: DataShades <datashades@linkdigital.com.au>, Oleksandr Cherniavskyi <mutantsan@gmail.com>
Maintainer-email: DataShades <datashades@linkdigital.com.au>
License: AGPL
Project-URL: Homepage, https://github.com/DataShades/ckanext-unfold
Keywords: CKAN
Classifier: Development Status :: 4 - Beta
Classifier: License :: OSI Approved :: GNU Affero General Public License v3 or later (AGPLv3+)
Classifier: Programming Language :: Python :: 3.11
Classifier: Programming Language :: Python :: 3.12
Classifier: Programming Language :: Python :: 3.13
License-File: LICENSE
Requires-Dist: rarfile>=4.0
Requires-Dist: py7zr>=0.20.6
Requires-Dist: rpmfile>=1.1.1
Requires-Dist: pydantic<3.0.0,>=2.3.0
Requires-Dist: ar<2.0.0,>=1.0.0
Requires-Dist: zstandard<1.0.0,>=0.21.0
Provides-Extra: dev
Requires-Dist: pytest-ckan; extra == "dev"
Dynamic: license-file
